hivemind_redis_database/__init__.py
hivemind_redis_database/version.py
hivemind_redis_database-0.0.2.dist-info/LICENSE.md
hivemind_redis_database-0.0.2.dist-info/METADATA
hivemind_redis_database-0.0.2.dist-info/WHEEL
hivemind_redis_database-0.0.2.dist-info/entry_points.txt
hivemind_redis_database-0.0.2.dist-info/top_level.txt
hivemind_redis_database-0.0.2.dist-info/RECORD
