Metadata-Version: 2.1
Name: hivemind-redis-database
Version: 0.0.2
Summary: redis database plugin for hivemind-core
Home-page: https://github.com/JarbasHiveMind/hivemind-redis-database
Author: jarbasAi
Author-email: jarbasai@mailfence.com
License: Apache-2.0
Platform: UNKNOWN
Requires-Dist: py-redis
Requires-Dist: hivemind-plugin-manager<1.0.0,>=0.1.0
